LICENSE
README.md
setup.py
blind_video_watermark/__init__.py
blind_video_watermark/client.py
blind_video_watermark/dtcwt_img.py
blind_video_watermark/dtcwt_key.py
blind_video_watermark/utils.py
blind_video_watermark.egg-info/PKG-INFO
blind_video_watermark.egg-info/SOURCES.txt
blind_video_watermark.egg-info/dependency_links.txt
blind_video_watermark.egg-info/entry_points.txt
blind_video_watermark.egg-info/requires.txt
blind_video_watermark.egg-info/top_level.txt